bdsms/__init__.py
bdsms/bdsms.py
bdsms-0.0.1.dist-info/LICENSE
bdsms-0.0.1.dist-info/METADATA
bdsms-0.0.1.dist-info/WHEEL
bdsms-0.0.1.dist-info/entry_points.txt
bdsms-0.0.1.dist-info/top_level.txt
bdsms-0.0.1.dist-info/RECORD
