Metadata-Version: 2.1
Name: bdsms
Version: 0.0.1
Summary: BD SMS BOMBER
Home-page: https://github.com/AKXVAU
Author: AKXVAU
Author-email: akxvau@gmail.com
License: MIT
Keywords: hacker,spam,tool,sms,bomber,call,prank,termux,hack,sms bomber,sms bomber,AKXVAU
Platform: UNKNOWN
Classifier: Development Status :: 4 - Beta
Classifier: Intended Audience :: Developers
Classifier: Topic :: Software Development :: Libraries :: Python Modules
Classifier: License :: OSI Approved :: MIT License
Classifier: Programming Language :: Python :: 3
Classifier: Operating System :: OS Independent
Classifier: Environment :: Console
Requires-Python: >=3.9
License-File: LICENSE
Requires-Dist: lolcat
Requires-Dist: requests
